craterstats/Chronologyfn.py
craterstats/Cratercount.py
craterstats/Craterpdf.py
craterstats/Craterplot.py
craterstats/Craterplotset.py
craterstats/Epochs.py
craterstats/Productionfn.py
craterstats/Randomnessanalysis.py
craterstats/Spatialcount.py
craterstats/__init__.py
craterstats/cli.py
craterstats/constants.py
craterstats/miscellaneous.py
craterstats/config/_AREA.qml
craterstats/config/_CRATER.qml
craterstats/config/__init__.py
craterstats/config/demo_commands.txt
craterstats/config/functions.txt
craterstats/fonts/OFL.txt
"craterstats/fonts/OpenSans-Italic-VariableFont_wdth,wght.ttf"
"craterstats/fonts/OpenSans-VariableFont_wdth,wght.ttf"
craterstats/gm/__init__.py
craterstats/gm/file/__init__.py
craterstats/gm/file/file_exists.py
craterstats/gm/file/filename.py
craterstats/gm/file/read_textfile.py
craterstats/gm/file/read_textstructure.py
craterstats/gm/file/write_textfile.py
craterstats/gm/idl/__init__.py
craterstats/gm/idl/value_locate.py
craterstats/gm/idl/where.py
craterstats/gm/maths/__init__.py
craterstats/gm/maths/normal.py
craterstats/gm/maths/poisson.py
craterstats/gm/maths/poly.py
craterstats/gm/maths/range.py
craterstats/gm/maths/scl.py
craterstats/gm/plotting/__init__.py
craterstats/gm/plotting/mix_colours.py
craterstats/gm/plotting/mpl_check_font.py
craterstats/gm/plotting/shp_plot_polygon.py
craterstats/gm/plotting/ticks.py
craterstats/gm/string/__init__.py
craterstats/gm/string/bright.py
craterstats/gm/string/diameter_range.py
craterstats/gm/string/percentile_sigfigs.py
craterstats/gm/string/quoted_split.py
craterstats/gm/string/scientific_notation.py
craterstats/gm/string/sigfigs.py
craterstats/gm/string/strip_quotes.py
craterstats/sample/CE-6 8-km vicinity.scc
craterstats/sample/CE-6 8-km vicinity_ra.txt
craterstats/sample/ECHUS_CHAP_AR1_A.stat
craterstats/sample/Im2.scc
craterstats/sample/Pickering.scc
craterstats/sample/README.md
craterstats/sample/__init__.py
craterstats/sample/c1.scc
craterstats/sample/c2.scc
craterstats/sample/c3.scc
craterstats-3.6.3.dist-info/licenses/LICENSE.txt
craterstats-3.6.3.dist-info/METADATA
craterstats-3.6.3.dist-info/WHEEL
craterstats-3.6.3.dist-info/entry_points.txt
craterstats-3.6.3.dist-info/top_level.txt
craterstats-3.6.3.dist-info/RECORD
