Metadata-Version: 2.4
Name: craterstats
Version: 3.6.3
Summary: Craterstats - a tool to analyse and plot crater count data for planetary surface dating
Home-page: https://github.com/ggmichael/craterstats
Author: Greg Michael
Author-email: ggmichael@users.noreply.github.com
License: BSD license
Keywords: planetary,chronology,crater
Classifier: Development Status :: 5 - Production/Stable
Classifier: License :: OSI Approved :: BSD License
Classifier: Natural Language :: English
Classifier: Programming Language :: Python :: 3.12
Requires-Python: >=3.12
License-File: LICENSE.txt
Requires-Dist: astropy-healpix
Requires-Dist: colorama
Requires-Dist: matplotlib
Requires-Dist: numpy
Requires-Dist: palettable
Requires-Dist: progressbar2
Requires-Dist: pyproj
Requires-Dist: pyshp
Requires-Dist: scipy>=1.14
Requires-Dist: shapely
Requires-Dist: spherely
Dynamic: author
Dynamic: author-email
Dynamic: classifier
Dynamic: description
Dynamic: description-content-type
Dynamic: home-page
Dynamic: keywords
Dynamic: license
Dynamic: license-file
Dynamic: requires-dist
Dynamic: requires-python
Dynamic: summary
